user_manager/mongoengine.py
user_manager/user_manager.py
user_manager-2.2.dist-info/DESCRIPTION.rst
user_manager-2.2.dist-info/METADATA
user_manager-2.2.dist-info/RECORD
user_manager-2.2.dist-info/WHEEL
user_manager-2.2.dist-info/metadata.json
user_manager-2.2.dist-info/top_level.txt
